alertist/__init__.py
alertist/conf.py
alertist/targets/__init__.py
alertist/targets/abstract.py
alertist/targets/pushover.py
alertist-0.1.0.dist-info/LICENSE
alertist-0.1.0.dist-info/METADATA
alertist-0.1.0.dist-info/WHEEL
alertist-0.1.0.dist-info/RECORD
