Metadata-Version: 2.1
Name: alertist
Version: 0.1.0
Summary: A general purpose library for sending alerts
License: MIT
Author: Your Name
Author-email: you@example.com
Requires-Python: >=3.11,<4.0
Classifier: License :: OSI Approved :: MIT License
Classifier: Programming Language :: Python :: 3
Classifier: Programming Language :: Python :: 3.11
Classifier: Programming Language :: Python :: 3.12
Requires-Dist: httpx (>=0.27.0,<0.28.0)
Requires-Dist: python-dotenv (>=1.0.1,<2.0.0)
